perf_logger/__init__.py
perf_logger/perf_logger.py
perf_logger/utils.py
perf_logger-0.9.55555.dist-info/METADATA
perf_logger-0.9.55555.dist-info/WHEEL
perf_logger-0.9.55555.dist-info/top_level.txt
perf_logger-0.9.55555.dist-info/RECORD
