Metadata-Version: 2.1
Name: perf-logger
Version: 0.9.55555
Summary: performance logger of training deep networks.
Home-page: UNKNOWN
License: UNKNOWN
Platform: UNKNOWN
Requires-Python: >=3.6.3
Requires-Dist: numpy (>=1.2.0)
